simplet5_trl/__init__.py
simplet5_trl/simplet5_trl.py
simplet5_trl-0.2.0.dist-info/licenses/LICENSE
simplet5_trl-0.2.0.dist-info/METADATA
simplet5_trl-0.2.0.dist-info/WHEEL
simplet5_trl-0.2.0.dist-info/top_level.txt
simplet5_trl-0.2.0.dist-info/RECORD
