Metadata-Version: 2.4
Name: simplet5-trl
Version: 0.2.0
Summary: simpleT5-TRL is built on top of HuggingFace Transformers and TRL that lets you quickly train encoder-decoder models (T5, BART, T5Gemma, etc.) with full finetuning, LoRA, QLoRA, DPO, SimPO, and RFT support.
Author-email: Siddharth Deshpande <siddharth.deshpande63@gmail.com>
License-Expression: MIT
Project-URL: Homepage, https://github.com/siddharth0112358/simpleT5_TRL
Project-URL: Repository, https://github.com/siddharth0112358/simpleT5_TRL
Project-URL: Bug Tracker, https://github.com/siddharth0112358/simpleT5_TRL/issues
Keywords: T5,simpleT5-TRL,transformers,NLP,finetune,fine-tuning,pytorch,summarization,translation,training,classification,Q&A,inference,fast inference,LoRA,QLoRA,PEFT,BART,encoder-decoder,T5Gemma,TRL,Seq2SeqTrainer,DPO,SimPO,RFT,RLHF,preference-optimization,alignment
Classifier: Intended Audience :: Developers
Classifier: Topic :: Scientific/Engineering :: Artificial Intelligence
Classifier: Programming Language :: Python :: 3
Classifier: Programming Language :: Python :: 3.9
Classifier: Programming Language :: Python :: 3.10
Classifier: Programming Language :: Python :: 3.11
Classifier: Programming Language :: Python :: 3.12
Requires-Python: >=3.9
License-File: LICENSE
Requires-Dist: numpy==1.26.4
Requires-Dist: pandas==1.3.5
Requires-Dist: scipy==1.15.0
Requires-Dist: sentencepiece==0.2.1
Requires-Dist: torch==2.9.1
Requires-Dist: transformers==5.0.0rc1
Requires-Dist: trl==0.26.2
Requires-Dist: peft==0.18.0
Requires-Dist: bitsandbytes==0.49.0
Requires-Dist: accelerate==1.12.0
Requires-Dist: datasets>=2.14.0
Requires-Dist: rouge-score>=0.1.2
Requires-Dist: torchaudio==2.9.1
Requires-Dist: torchvision==0.24.1
Requires-Dist: tf-keras==2.20.1
Requires-Dist: pillow==12.0.0
Dynamic: license-file
